{
  "fighter": "Brandon Davis",
  "slug": "brandon-davis",
  "appearances": 2,
  "walkouts": [
    {
      "song_title": "",
      "artist": "",
      "confidence": "missing",
      "spotify_url": "",
      "event": "UFC 236: Holloway vs. Poirier 2",
      "event_slug": "ufc-236",
      "date": "2019-04-13"
    },
    {
      "song_title": "",
      "artist": "",
      "confidence": "missing",
      "spotify_url": "",
      "event": "UFC 241: Cormier vs. Miocic 2",
      "event_slug": "ufc-241",
      "date": "2019-08-17"
    }
  ],
  "stats": {
    "events": 2,
    "with_song": 0,
    "missing": 2,
    "unique_songs": 0
  }
}