{
  "fighter": "CJ Vergara",
  "slug": "cj-vergara",
  "appearances": 3,
  "walkouts": [
    {
      "song_title": "",
      "artist": "“CAN'T TELL ME NOTHING” by Kanye West « Previous Kamaru Usman, Rose Namajunas Retain Championships in Route-Going Efforts at UFC 268 Next By the Numbers: UFC 268 » More view more --> Junior dos Santos: Alex Pereira has ideal matchup for heavyweight debutUFC Seattle main card finalized with late changeLerone Murphy shares extent of hip injury suffered in UFC London headlinerShillan & Duffy: UFC Seattle previewArman Tsarukyan wary of Georgio Poullas: 'He’s like a rat' Subscribe to our Newsletter * indicates required Email Address * Latest News ALLUFCPFL Junior dos Santos: Alex Pereira has ideal matchup for heavyweight debutUFC Seattle main card finalized with late changeLerone Murphy shares extent of hip injury suffered in UFC London headlinerArman Tsarukyan wary of Georgio Poullas: 'He’s like a rat'Joel Alvarez names hardest puncher he’s ever facedKhabib Nurmagomedov congratulates Movsar Evloev on UFC London victoryMassive payday rumored for Nate Diaz on MVP cardArman Tsarukyan offers to 'save the featherweight division' after UFC LondonJunior dos Santos: Alex Pereira has ideal matchup for heavyweight debutUFC Seattle main card finalized with late changeLerone Murphy shares extent of hip injury suffered in UFC London headlinerArman Tsarukyan wary of Georgio Poullas: 'He’s like a rat'Joel Alvarez names hardest puncher he’s ever facedKhabib Nurmagomedov congratulates Movsar Evloev on UFC London victoryArman Tsarukyan offers to 'save the featherweight division' after UFC LondonAljamain Sterling questions scoring of UFC London headlinerCostello van Steenis leaves no doubt against Fabian Edwards at PFL MadridPFL Madrid ‘Van Steenis vs. Edwards 2’ play-by-play, results & round scoringJoe Schilling to return at PFL Brussels against fellow ex-kickboxerPFL Madrid weigh-in results: Middleweight title fight setFull Card Official for PFL Africa on April 10Heavyweight matchup added to PFL ChicagoPFL announces release of former heavyweight king Francis NgannouStreaking French bantamweight meets fellow UFC veteran at PFL Brussels EVENTS / FIGHTS UFCPFL MORE Mar282026 UFC Fight Night 271 Adesanya vs. Pyfer Apr042026 UFC Fight Night 272 Moicano vs. Duncan Apr112026 UFC 327 Prochazka vs. Ulberg Apr182026 UFC Fight Night 273 Burns vs. Malott Apr252026 UFC Fight Night 274 Sterling vs. Zalal Mar282026 Professional Fighters League PFL Pittsburgh - Eblen vs. Battle Apr102026 Professional Fighters League PFL Africa 1: 2026 First Round Apr112026 Professional Fighters League PFL Chicago - Pettis vs. McKee Apr162026 Professional Fighters League PFL Belfast - Hughes vs. Wilson May022026 Professional Fighters League PFL Sioux Falls - Storley vs. Zendeli + MORE UFC FIGHTS+ MORE PFL FIGHTS {firstname} { \"nickname\" }{lastname} {firstname} { \"nickname\" }{lastname} {name} - {title} FIGHT FINDER FIGHTER OF THE WEEK Ariane Lipski da Silva TOP TRENDING FIGHTERS Joe PyferJohnny EblenIsrael AdesanyaBryan Battle MORE FIGHTERS... Mansur Abdul-Malik",
      "confidence": "missing",
      "spotify_url": "",
      "event": "UFC 268",
      "event_slug": "ufc-268",
      "date": "2021-11-06"
    },
    {
      "song_title": "CAN'T TELL ME NOTHING",
      "artist": "Kanye West",
      "confidence": "bronze",
      "spotify_url": "https://open.spotify.com/track/0mEdbdeRFQwBhN4xfyIeUM",
      "event": "UFC 274",
      "event_slug": "ufc-274",
      "date": "2022-05-07"
    },
    {
      "song_title": "Utah Freestyle",
      "artist": "Russ",
      "confidence": "bronze",
      "spotify_url": "https://open.spotify.com/track/5g6wdIeJk6dIRfrCQ2ABq5",
      "event": "UFC 291",
      "event_slug": "ufc-291",
      "date": "2023-07-29"
    }
  ],
  "stats": {
    "events": 3,
    "with_song": 2,
    "missing": 1,
    "unique_songs": 2
  }
}