{
  "fighter": "Daniel Teymur",
  "slug": "daniel-teymur",
  "appearances": 2,
  "walkouts": [
    {
      "song_title": "",
      "artist": "",
      "confidence": "missing",
      "spotify_url": "",
      "event": "UFC 245: Usman vs. Covington",
      "event_slug": "ufc-245",
      "date": "2019-12-14"
    },
    {
      "song_title": "",
      "artist": "",
      "confidence": "missing",
      "spotify_url": "",
      "event": "UFC Fight Night: Nelson vs. Ponzinibbio",
      "event_slug": "ufc-fight-night-nelson-vs-ponzinibbio",
      "date": "2017-07-16"
    }
  ],
  "stats": {
    "events": 2,
    "with_song": 0,
    "missing": 2,
    "unique_songs": 0
  }
}