{
  "fighter": "Garreth McLellan",
  "slug": "garreth-mclellan",
  "appearances": 2,
  "walkouts": [
    {
      "song_title": "Thunderstruck",
      "artist": "AC/DC",
      "confidence": "bronze",
      "spotify_url": "https://open.spotify.com/track/57bgtoPSgt236HzfBOd8kj",
      "event": "UFC Fight Night: Overeem vs Arlovski",
      "event_slug": "ufc-fight-night-overeem-vs-arlovski",
      "date": "2016-05-08"
    },
    {
      "song_title": "Thunderstruck",
      "artist": "AC/DC",
      "confidence": "bronze",
      "spotify_url": "https://open.spotify.com/track/57bgtoPSgt236HzfBOd8kj",
      "event": "UFC on FOX: Maia vs. Condit",
      "event_slug": "ufc-on-fox-maia-vs-condit",
      "date": "2016-08-27"
    }
  ],
  "stats": {
    "events": 2,
    "with_song": 2,
    "missing": 0,
    "unique_songs": 1
  }
}