{
  "fighter": "Josh Burkman",
  "slug": "josh-burkman",
  "appearances": 1,
  "walkouts": [
    {
      "song_title": "The Baddest Man Alive",
      "artist": "The Black Keys & RZA",
      "confidence": "bronze",
      "spotify_url": "https://open.spotify.com/track/2Gg9tkVjRYoZHhXzBeYyuV",
      "event": "UFC 214: Cormier vs. Jones 2",
      "event_slug": "ufc-214",
      "date": "2017-07-29"
    }
  ],
  "stats": {
    "events": 1,
    "with_song": 1,
    "missing": 0,
    "unique_songs": 1
  }
}