{
  "fighter": "Phil Hawes",
  "slug": "phil-hawes",
  "appearances": 6,
  "walkouts": [
    {
      "song_title": "",
      "artist": "",
      "confidence": "missing",
      "spotify_url": "",
      "event": "UFC Fight Night: Ankalaev vs. Walker 2",
      "event_slug": "ufc-fight-night-ankalaev-vs-walker-2",
      "date": "2024-01-13"
    },
    {
      "song_title": "Electrifying the Rock",
      "artist": "Jim Johnston",
      "confidence": "bronze",
      "spotify_url": "https://open.spotify.com/track/76kjXpUTrh4RDeX0OE9h7r",
      "event": "UFC 288: Sterling vs. Cejudo",
      "event_slug": "ufc-288",
      "date": "2023-05-06"
    },
    {
      "song_title": "",
      "artist": "",
      "confidence": "missing",
      "spotify_url": "",
      "event": "UFC Fight Night: Kattar vs. Allen",
      "event_slug": "ufc-fight-night-kattar-vs-allen",
      "date": "2022-10-29"
    },
    {
      "song_title": "",
      "artist": "",
      "confidence": "missing",
      "spotify_url": "",
      "event": "UFC Fight Night: Kattar vs. Emmett",
      "event_slug": "ufc-fight-night-kattar-vs-emmett",
      "date": "2022-06-18"
    },
    {
      "song_title": "UNCHAINED",
      "artist": "",
      "confidence": "bronze",
      "spotify_url": "https://open.spotify.com/track/2qhASBzpbFhPRtrnZ5lLnz",
      "event": "UFC 268: Usman vs. Covington 2",
      "event_slug": "ufc-268",
      "date": "2021-11-06"
    },
    {
      "song_title": "",
      "artist": "",
      "confidence": "missing",
      "spotify_url": "",
      "event": "UFC 254: Khabib vs. Gaethje",
      "event_slug": "ufc-254",
      "date": "2020-10-24"
    }
  ],
  "stats": {
    "events": 6,
    "with_song": 2,
    "missing": 4,
    "unique_songs": 2
  }
}