{
  "event": "UFC Fight Night: Lewis vs. Nascimento",
  "event_slug": "ufc-fight-night-lewis-vs-nascimento",
  "date": "2024-05-11",
  "location": "St. Louis, Missouri, USA",
  "source_urls": [
    "https://www.inkl.com/news/fight-tracks-the-walkout-songs-of-ufc-fight-night-231-coolio-cranberries-europe-in-brazil"
  ],
  "generated_at": "2026-03-29",
  "songs": [
    {
      "fighter": "Derrick Lewis",
      "song_title": "Tops Drop",
      "artist": "Fat Pat",
      "confidence": "bronze",
      "spotify_url": "https://open.spotify.com/track/5oS8YDcBrOzRV3H437J9m5",
      "notes": ""
    },
    {
      "fighter": "Rodrigo Nascimento",
      "song_title": "Capitulo 4, Versiculo 3",
      "artist": "Racionais MCs",
      "confidence": "bronze",
      "spotify_url": "https://open.spotify.com/track/6Wt61AZLG0bN2KasopE2sj",
      "notes": ""
    },
    {
      "fighter": "Joaquin Buckley",
      "song_title": "",
      "artist": "",
      "confidence": "missing",
      "spotify_url": "",
      "notes": ""
    },
    {
      "fighter": "Nursulton Ruziboev",
      "song_title": "",
      "artist": "",
      "confidence": "missing",
      "spotify_url": "",
      "notes": ""
    },
    {
      "fighter": "Carlos Ulberg",
      "song_title": "",
      "artist": "",
      "confidence": "missing",
      "spotify_url": "",
      "notes": ""
    },
    {
      "fighter": "Alonzo Menifield",
      "song_title": "",
      "artist": "",
      "confidence": "missing",
      "spotify_url": "",
      "notes": ""
    },
    {
      "fighter": "Diego Ferreira",
      "song_title": "",
      "artist": "",
      "confidence": "missing",
      "spotify_url": "",
      "notes": ""
    },
    {
      "fighter": "Mateusz Rebecki",
      "song_title": "",
      "artist": "",
      "confidence": "missing",
      "spotify_url": "",
      "notes": ""
    },
    {
      "fighter": "Sean Woodson",
      "song_title": "",
      "artist": "",
      "confidence": "missing",
      "spotify_url": "",
      "notes": ""
    },
    {
      "fighter": "Alex Caceres",
      "song_title": "",
      "artist": "",
      "confidence": "missing",
      "spotify_url": "",
      "notes": ""
    },
    {
      "fighter": "Waldo Cortes Acosta",
      "song_title": "",
      "artist": "",
      "confidence": "missing",
      "spotify_url": "",
      "notes": ""
    },
    {
      "fighter": "Robelis Despaigne",
      "song_title": "",
      "artist": "",
      "confidence": "missing",
      "spotify_url": "",
      "notes": ""
    },
    {
      "fighter": "Chase Hooper",
      "song_title": "",
      "artist": "",
      "confidence": "missing",
      "spotify_url": "",
      "notes": ""
    },
    {
      "fighter": "Viacheslav Borshchev",
      "song_title": "",
      "artist": "",
      "confidence": "missing",
      "spotify_url": "",
      "notes": ""
    },
    {
      "fighter": "Esteban Ribovics",
      "song_title": "",
      "artist": "",
      "confidence": "missing",
      "spotify_url": "",
      "notes": ""
    },
    {
      "fighter": "Terrance McKinney",
      "song_title": "",
      "artist": "",
      "confidence": "missing",
      "spotify_url": "",
      "notes": ""
    },
    {
      "fighter": "Tabatha Ricci",
      "song_title": "",
      "artist": "",
      "confidence": "missing",
      "spotify_url": "",
      "notes": ""
    },
    {
      "fighter": "Tecia Pennington",
      "song_title": "",
      "artist": "",
      "confidence": "missing",
      "spotify_url": "",
      "notes": ""
    },
    {
      "fighter": "Trey Waters",
      "song_title": "",
      "artist": "",
      "confidence": "missing",
      "spotify_url": "",
      "notes": ""
    },
    {
      "fighter": "Billy Ray Goff",
      "song_title": "",
      "artist": "",
      "confidence": "missing",
      "spotify_url": "",
      "notes": ""
    },
    {
      "fighter": "Charles Johnson",
      "song_title": "",
      "artist": "",
      "confidence": "missing",
      "spotify_url": "",
      "notes": ""
    },
    {
      "fighter": "Jake Hadley",
      "song_title": "",
      "artist": "",
      "confidence": "missing",
      "spotify_url": "",
      "notes": ""
    },
    {
      "fighter": "Veronica Hardy",
      "song_title": "",
      "artist": "",
      "confidence": "missing",
      "spotify_url": "",
      "notes": ""
    },
    {
      "fighter": "JJ Aldrich",
      "song_title": "",
      "artist": "",
      "confidence": "missing",
      "spotify_url": "",
      "notes": ""
    }
  ]
}
